gsheet_table_sync/__init__.py
gsheet_table_sync/gsheet_table_sync.py
gsheet_table_sync-0.4.1.dist-info/DESCRIPTION.rst
gsheet_table_sync-0.4.1.dist-info/METADATA
gsheet_table_sync-0.4.1.dist-info/RECORD
gsheet_table_sync-0.4.1.dist-info/WHEEL
gsheet_table_sync-0.4.1.dist-info/metadata.json
gsheet_table_sync-0.4.1.dist-info/top_level.txt
