Metadata-Version: 2.0
Name: gsheet-table-sync
Version: 0.4.1
Summary: keeping google sheet data in sync
Home-page: https://github.com/asetiawan/gsheet_table_sync
Author: nottony
Author-email: nottony-pypi@yahoo.com
License: MIT
Platform: UNKNOWN
Requires-Python: >=3.3
Requires-Dist: google-api-python-client
Requires-Dist: google-auth
